qaintum_qnn/__init__.py
qaintum_qnn/layers/__init__.py
qaintum_qnn/layers/qnn_circuit.py
qaintum_qnn/layers/qnn_data_encoder.py
qaintum_qnn/layers/qnn_layer.py
qaintum_qnn/models/__init__.py
qaintum_qnn/models/quantum_neural_network.py
qaintum_qnn/utils/__init__.py
qaintum_qnn/utils/normalization.py
qaintum_qnn/utils/qnn_weight_init.py
qnn_examples/advanced_features.py
qnn_examples/basic_usage.py
qnn_examples/bio_oil_projection/__init__.py
qnn_examples/bio_oil_projection/custom_encoder.py
qnn_examples/bio_oil_projection/train.py
qnn_examples/cancer_diagnosis/data_processing.py
qnn_examples/cancer_diagnosis/model_builder.py
qnn_examples/cancer_diagnosis/train.py
qnn_examples/cancer_diagnosis/training_utils.py
qnn_examples/cancer_diagnosis/visualization.py
tests/__init__.py
tests/test_advanced_features.py
tests/test_basic_usage.py
tests/test_normalization.py
tests/test_qnn_circuit.py
tests/test_qnn_data_encoder.py
tests/test_qnn_layer.py
tests/test_qnn_weight_init.py
tests/test_quantum_neural_network.py
qaintum_qnn-0.1.1.dist-info/METADATA
qaintum_qnn-0.1.1.dist-info/WHEEL
qaintum_qnn-0.1.1.dist-info/top_level.txt
qaintum_qnn-0.1.1.dist-info/RECORD
