Metadata-Version: 2.4
Name: qaintum_qnn
Version: 0.1.1
Summary: Quantum Neural Networks (QNN) framework for quantum-enhanced machine learning.
Home-page: https://github.com/qaintumai/qaintum-ai/tree/main/qnn-container
Author: Sophie Choe, Alex Olivas, Max Ivry, B R Nikilesh
Author-email: Sophie Choe <sophie.choe@qaintum.ai>, Alex Olivas <alex.r.olivas@gmail.com>, Max Ivry <maxssivry@gmail.com>, B R Nikilesh <brnikilesh7@gmail.com>
License: MIT
Project-URL: Homepage, https://github.com/qaintumai/qaintum-ai/tree/main/qnn-container
Project-URL: Documentation, https://github.com/qaintumai/qaintum-ai/tree/main/qnn-container/docs
Project-URL: Repository, https://github.com/qaintumai/qaintum-ai/tree/main/qnn-container
Requires-Python: >=3.8
Requires-Dist: torch<2.3,>=2.2
Requires-Dist: torchvision<0.18,>=0.17
Requires-Dist: PennyLane<0.30,>=0.29
Requires-Dist: PennyLane-SF<0.30,>=0.29
Requires-Dist: numpy<1.24,>=1.23
Requires-Dist: scipy<1.11,>=1.10
Requires-Dist: sympy>=1.10
Provides-Extra: dev
Requires-Dist: pytest; extra == "dev"
Requires-Dist: black; extra == "dev"
Requires-Dist: flake8; extra == "dev"
Requires-Dist: mypy; extra == "dev"
Requires-Dist: pre-commit; extra == "dev"
Requires-Dist: pytest-cov; extra == "dev"
